{
  "last_seen_submission": "",
  "last_seen_comment": "",
  "welcomed_posts": [
    "1p20bls",
    "1p36hdm",
    "1p6vk29",
    "1p765bd",
    "1p7644s",
    "1p76kje",
    "1p7yk3s",
    "1p81xt8",
    "1p81vow",
    "1p8n7nh",
    "1p9s63b",
    "1p9s4wc",
    "1p9s36p",
    "1p9sidp",
    "1p9ses0",
    "1p9v24v",
    "1p9vse0",
    "1pa2fk1",
    "1pa2mq2",
    "1pa3cjn",
    "1pa36kc",
    "1pa3gzi",
    "1pa5zdj",
    "1pa6sve",
    "1pa7gzh",
    "1pa8o55",
    "1pa8z31",
    "1pa8y97",
    "1pa8xt4",
    "1pa8xbi",
    "1paaa77",
    "1pab9pr",
    "1pab8ns",
    "1pabqxf",
    "1paepgb",
    "1paep8h",
    "1paeozu",
    "1pafsa3",
    "1pafrme",
    "1pakett",
    "1pam3x4",
    "1paqqdl",
    "1paqv1w",
    "1parcnu",
    "1parchl",
    "1pasfhc",
    "1pasyll",
    "1pat5gr",
    "1patfzs",
    "1patcqt",
    "1patvw2",
    "1pb4u0b",
    "1pb9hhb",
    "1pbcux7",
    "1pbeydx",
    "1pbn5yh",
    "1pbn5be",
    "1pbn4ey",
    "1pboe3i",
    "1pbolfd",
    "1pbokvq",
    "1pbokjh",
    "1pbpa3r",
    "1pbsigq",
    "1pbsr4x",
    "1pbsxvf",
    "1pbsve7",
    "1pbya8z",
    "1pbz4fy",
    "1pbz9dv",
    "1pbzuis",
    "1pc0985",
    "1pc053e",
    "1pc03h4",
    "1pc0be6",
    "1pc0t03",
    "1pc42ci",
    "1pc7rjb",
    "1pc7rbl",
    "1pc965a",
    "1pcc9w0",
    "1pcdev1",
    "1pcdegt",
    "1pcde9i",
    "1pcddyz",
    "1pcg5hf",
    "1pcgq4y",
    "1pch2jo",
    "1pcm5ts",
    "1pcob5e",
    "1pcr0dp",
    "1pcwxjw",
    "1pcx98w",
    "1pcxx0e",
    "1pcy9mn",
    "1pcyuz9",
    "1pd020s",
    "1pd4xff",
    "1pddsab",
    "1pdjprh",
    "1pdk6xl",
    "1pdk6vh",
    "1pdnw3t",
    "1pdtz9z",
    "1pdtxej",
    "1pdtwjw",
    "1pe5he8",
    "1pebhwu",
    "1pecn4u",
    "1peddsq",
    "1peeu2u",
    "1pendfg",
    "1pen9ib",
    "1peuus1",
    "1peuul6",
    "1peuubp",
    "1pevk92",
    "1pew5uy",
    "1pexdyw",
    "1pexpl6",
    "1peya34",
    "1pezjts",
    "1pf78xa",
    "1pf9aah",
    "1pfaa69",
    "1pfg7oo",
    "1pfgbd3",
    "1pfqzxc",
    "1pfrfn1",
    "1pfrr6c",
    "1pfts1g",
    "1pftrub",
    "1pfuqis",
    "1pfv8u3",
    "1pfyzz3",
    "1pgdzu0",
    "1pgid2u",
    "1pgj7ca",
    "1pgjtx5",
    "1pgkisa",
    "1pgmuno",
    "1pgnjd0",
    "1pgo738",
    "1pgo6fd",
    "1pgo0xx",
    "1pgoc5z",
    "1pgotof",
    "1pgv0s9",
    "1pgvahv",
    "1pgva8g",
    "1pgvxa8",
    "1pgwwlf",
    "1pgx2pr",
    "1pgx2hb",
    "1pgx29n",
    "1ph7guj",
    "1ph9c0w",
    "1ph9tl6",
    "1phfiut",
    "1phhfer",
    "1phheeb",
    "1phhaf0",
    "1phjivy",
    "1phnnfx",
    "1phqo2h",
    "1phqbm9",
    "1phs86s",
    "1phtx7i",
    "1phxbng",
    "1pi90gx",
    "1picw43",
    "1pidfdd",
    "1pifla0",
    "1pig1ns",
    "1pihc4g",
    "1pii0s0",
    "1pihyr2",
    "1pil1dw",
    "1pilueh",
    "1pilttd",
    "1pimrct",
    "1pisteh",
    "1piugxl",
    "1pj9qks",
    "1pj9qa6",
    "1pjcwv5",
    "1pjev8h",
    "1pjerb0",
    "1pjeqkh",
    "1pjeop2",
    "1pjgepn",
    "1pjhxt3",
    "1pjlw7k",
    "1pjucz7",
    "1pjxml2",
    "1pjyqoo",
    "1pjyljb",
    "1pk0ezk",
    "1pk1ef7",
    "1pk3p0f",
    "1pkeagq",
    "1pkea5x",
    "1pke9pw",
    "1pkg9g0",
    "1pkg88y",
    "1pki7pf",
    "1pki635",
    "1pkin55",
    "1pkidwv",
    "1pkmu8g",
    "1pknmxy",
    "1pkpmwb",
    "1pkr1gf",
    "1pksp92",
    "1pkthtr",
    "1pkturx",
    "1pl4mei",
    "1plgyvg",
    "1plhdyg",
    "1plivt7",
    "1plj2da",
    "1plmcbf",
    "1plo9y5",
    "1plp4lu",
    "1plp3z2",
    "1plp2o4",
    "1plpkeg",
    "1plqysy",
    "1plsp0o",
    "1pltm6g",
    "1plvtly",
    "1pm7cbf",
    "1pm9wwp",
    "1pm9w6w",
    "1pmdcdj",
    "1pmdnhy",
    "1pmeaia",
    "1pme98y",
    "1pmf41i",
    "1pmfh9k",
    "1pmgkuw",
    "1pmh8r2",
    "1pmih5p",
    "1pmjae7",
    "1pmlemd",
    "1pmmqee",
    "1pmqdg8",
    "1pmqynf",
    "1pn081c"
  ],
  "weekly_threads": {
    "leaderboard_post_id": "1pmkirq",
    "challenge_post_id": "1pmkisq"
  },
  "seen_posts": [
    "1poigxu",
    "1pp35j5",
    "1pnk78g",
    "1ppklu1",
    "1po1md2",
    "1pow8pt",
    "1ppk14i",
    "1ppzl3m",
    "1ppzyif",
    "1pogt47",
    "1pnuj4u",
    "1pnmfdb",
    "1pox1wc",
    "1po1upo",
    "1po85f3",
    "1pne9v6",
    "1po3qll",
    "1pp5omu",
    "1po91v2",
    "1ppkzn6",
    "1pogpa6",
    "1pnbx0t",
    "1ppzkgq",
    "1ppvfhh",
    "1pp9ove",
    "1po0nva",
    "1pp4nnp",
    "1pn3c26",
    "1pp2jum",
    "1ppq6gs",
    "1porcrf",
    "1po5aw6",
    "1povxi4",
    "1po7o48",
    "1pp6k80",
    "1ppkolf",
    "1ppq4zx",
    "1pp5p3m",
    "1pnk4yb",
    "1ppq9ok",
    "1pon32f",
    "1powc43",
    "1pozvig",
    "1pnkira",
    "1ppi9a9",
    "1po0o3b",
    "1po0nlf",
    "1powa3x",
    "1pppu65",
    "1pne3fr",
    "1po0n9s",
    "1pognak",
    "1pn92ej",
    "1pnq22j",
    "1ppk2gj",
    "1ppsg47",
    "1pn85a0",
    "1pogrdk",
    "1pnk5wn",
    "1ppuwya",
    "1po3y0c",
    "1por637",
    "1pni7zt",
    "1pp82td",
    "1por6du",
    "1pordm0",
    "1poipjk",
    "1ppzkpq",
    "1poc37v",
    "1pnbxn8",
    "1pord0y",
    "1pq1v2f",
    "1pngd7s",
    "1pp8yxl",
    "1pp6iis",
    "1po0ouz",
    "1pp5pe9",
    "1pprslz",
    "1pogqgn"
  ],
  "seen_comments": [
    "nu9mwrk",
    "nudmpbc",
    "nuilauz",
    "nulpz2k",
    "nunridf",
    "nuhfqu1",
    "nulmqzx",
    "nucmi92",
    "nufa5tp",
    "num3rxz",
    "nu5c5xq",
    "nuqeyg5",
    "nunpwvd",
    "nub4s42",
    "nukmgzp",
    "nue4u8e",
    "nuqg8td",
    "nuphgsc",
    "nunw56q",
    "nufnzn2",
    "nuc04su",
    "nuia82w",
    "nukupze",
    "nujfyko",
    "nujfluj",
    "nue7vy8",
    "nu6szlr",
    "nujj0g7",
    "nukssvr",
    "nuix14p",
    "numlm0u",
    "nuaq0zm",
    "nult5r5",
    "nulbaeo",
    "nueqz27",
    "nuk28wz",
    "nuk58sf",
    "numqd1h",
    "nujzyay",
    "nup3skb",
    "nugyitn",
    "nuflfcb",
    "numktv6",
    "nu5r4yf",
    "nulfbfv",
    "nugms4p",
    "nuk8k0q",
    "nucg8yk",
    "nuiz640",
    "nu57zkz",
    "nuevn6o",
    "nuemqhy",
    "nui93h8",
    "nu6lokt",
    "nuiaydx",
    "nuju4qe",
    "nud55xx",
    "nukb938",
    "nulpw9d",
    "nui1pr1",
    "nui14np",
    "numiymi",
    "nudt0c1",
    "nueqgh0",
    "nuidb9a",
    "numdw6o",
    "nuizx1t",
    "nud3s61",
    "nuiyppz",
    "nulyrgh",
    "nulounu",
    "nul7hpu",
    "num8ktm",
    "nui5uoq",
    "nuqcus4",
    "nufek51",
    "nu59jhj",
    "nuf5maa",
    "nu50onk",
    "nujn50a",
    "nump1fh",
    "nujs2gd",
    "nu6fjt9",
    "nuncq4b",
    "nukk9q5",
    "nuowasd",
    "nulk7on",
    "nuhfvcb",
    "nue2e7h",
    "nui7uwy",
    "nuiqqer",
    "nue40b2",
    "nuewu8c",
    "nuiiicn",
    "nu4dyub",
    "nue4jqd",
    "nudmll6",
    "nunuwq1",
    "nu9ho8b",
    "nufp1as",
    "nuprjnp",
    "nuhtlk0",
    "nuec550",
    "nu9e6qa",
    "nuatp0b",
    "nucrkd0",
    "nuo4sa7",
    "nudw6j2",
    "nul3l1w",
    "nuidups",
    "nuk8h2t",
    "nujakgu",
    "nuek7ev",
    "nuj5a63",
    "nueow1x",
    "nu5lwzu",
    "nu8egyu",
    "nulxn0e",
    "nupe8sw",
    "nu95zyi",
    "nuevy0g",
    "nuiwuc1",
    "nufczkl",
    "nueq6fh",
    "nul2jhm",
    "nunvrzf",
    "numnqj8",
    "nugwusp",
    "nufggu9",
    "nufbrq3",
    "num9pg9",
    "nucuinp",
    "nuqcq1r",
    "nugpj0u",
    "nufib8c",
    "nu9wy7s",
    "nulg7ox",
    "nukni62",
    "nuouarr",
    "nu8sj3b",
    "nugwdsb",
    "nunrnti",
    "nu9r3ug",
    "nucy8hc",
    "nue71uw",
    "nuku0id",
    "nujvlje",
    "nu7jpyh",
    "numi38r",
    "nuj9mvm",
    "nuf4wsn",
    "nuptvjl",
    "nui95ad",
    "nui17ui",
    "nueral1",
    "nugx9af",
    "nuhe0vz",
    "nukppp5",
    "nufrscw",
    "nuknz6l",
    "nu7o4rx",
    "nujteyr",
    "nukks0u",
    "nufpy3r",
    "nun66cb",
    "nuksdhn",
    "nudc9gp",
    "nu5rkuq",
    "nul368h",
    "nulyc2g",
    "nuht7kj",
    "nueqpso",
    "nuftfax",
    "nujazc3",
    "nuj1mce",
    "nugha1r",
    "nug9g7w",
    "nu6p9o6",
    "nujqogh",
    "nuoh9k8",
    "nunq6nf",
    "nul4xdc",
    "nu9a970",
    "nuitx7o",
    "nup88eh",
    "nujwg6r",
    "nultmrn",
    "nuazkwg",
    "nuf6e7a",
    "nuhzw6n",
    "nuiuqi8",
    "nukykul",
    "nulgukx",
    "nue2hps",
    "nuqavbb",
    "nugt6w9",
    "nu6n0eb",
    "nueqvsi",
    "nu4qlfr",
    "nuntce5",
    "nue0z42",
    "nua358y",
    "nuhxdvr",
    "nukd511",
    "nufd7fh",
    "nueka5a",
    "nul2jwi",
    "nu8ykz0",
    "nue2nv3",
    "nujggw4",
    "nuicq3a",
    "nu9wigg",
    "nujsehl",
    "nufj5tu",
    "nuiecka",
    "nunrozo",
    "nupes0z",
    "nuge49l",
    "nupmagy",
    "nu5fgo3",
    "nu7wcg2",
    "nujj7dc",
    "nufr3sa",
    "nuh5kf7",
    "nul49ff",
    "numn2xr",
    "nui6qq9",
    "nuqyqln",
    "nuilzbk",
    "nup2tcr",
    "nuo7txj",
    "nuek6j4",
    "nukwz4g",
    "nuoxq70",
    "nubj4pi",
    "nuk67a1",
    "nup3oe8",
    "nu6dx3y",
    "nue82e7",
    "nuog2kp",
    "nu7t3f2",
    "num1f7f",
    "nujfogl",
    "nulaike",
    "nud9t5g",
    "nu7ezdz",
    "numsar9",
    "nubviml",
    "nu5qprj",
    "nul4j3e",
    "nukx7q0",
    "nu8hiam",
    "nuee4qu",
    "nuarmz5",
    "nudsg4i",
    "nu7o9i0",
    "nuj2qn7",
    "nu5skht",
    "nuiyydi",
    "nukyxpf",
    "nudz9zh",
    "nulzlis",
    "nukeauf",
    "nu9fvmh",
    "nukojuc",
    "nu9lpnl",
    "nukuv7l",
    "nu9ouno",
    "nupfbcy",
    "nue8rqc",
    "nufz44y",
    "nukouke",
    "nukbzlp",
    "nueuc2u",
    "nufgzlt",
    "nuib9zv",
    "numamt7",
    "nui0m33",
    "nu9bn52",
    "nuh8gec",
    "nufk2qb",
    "nupwa2w",
    "nui06hy",
    "nu671ab",
    "nudhfng",
    "nui19op",
    "nuqxdsq",
    "nummt13",
    "nuiral2",
    "nuk56op",
    "num1asv",
    "nui50lt",
    "nujz5zn",
    "nukjm2d",
    "nuhhxxf",
    "nudmnsp",
    "nugaem9",
    "nu9pg2r",
    "nuindy1",
    "nueod80",
    "nuk6h9e",
    "nudamhy",
    "nukpc5v",
    "nueba3v",
    "nupyj5y",
    "nufq5e1",
    "nu6sxt7",
    "nuazhr9",
    "nuhm0e0",
    "nudmqns",
    "nu6q477",
    "nu6oiwf",
    "nu87438",
    "nujc5jc",
    "nulln2d",
    "nujy2ub",
    "nulvh23",
    "nu7nbqg",
    "nuitsm8",
    "nuecp5j",
    "nuqmt12",
    "nue13n7",
    "nufobih",
    "numjfk5",
    "nuj4cf3",
    "nufik57",
    "nuk9zch",
    "nuexk3v",
    "nuixdd7",
    "nun4084",
    "nukcp7w",
    "nuczjq6",
    "numdk33",
    "nujm0bc",
    "nuja05w",
    "nue7uod",
    "nudinzf",
    "numk7mx",
    "nuge7n9",
    "nue7f8n",
    "nudmeav",
    "nucm03v",
    "nuiwgpg",
    "nue1pmf",
    "nur1rss",
    "nudo9kc",
    "nul6wut",
    "nukvaab",
    "nuf9f9e",
    "nuo57c8",
    "nuk44js",
    "nuc38js",
    "nuc4x4r",
    "nuovi7w",
    "nuiwtzo",
    "nukipa0",
    "nudtjyh",
    "nucdi2x",
    "nu7c1fg",
    "nudf040",
    "nuf9j27",
    "nue5l6x",
    "num882p",
    "nulswab",
    "nubwxtu",
    "nud62zd",
    "nujowhz",
    "num59bn",
    "nugwtxw",
    "nufqu1u",
    "nulr43b",
    "nu4nlw2",
    "nul59gh",
    "nu9m9vx",
    "nufq0kf",
    "nud9wwh",
    "nuaqdpn",
    "nuei7ps",
    "num8vr7",
    "nun85kz",
    "nuncwn5",
    "nufmhov",
    "nu5mmj0",
    "nuiyrvu",
    "nulawjt",
    "nuglmti",
    "nufr7cs",
    "nupebn9",
    "nudxnzf",
    "nulmab1",
    "nukoaqs",
    "nulsvbl",
    "nue84ai",
    "nuilr6u",
    "nu91qrb",
    "nufp5z8",
    "nu8cxoj",
    "nufb50q",
    "nu95khy",
    "nukwhxn",
    "nuf4c9t",
    "numgr9b",
    "nulf7g7",
    "nu7l5s8",
    "nuea2c0",
    "nujnkmz",
    "nu9e7p2",
    "nuhmxpv",
    "nujf2mk",
    "nuj194h",
    "nuk5utl",
    "nuhzcxv",
    "nuobcp8",
    "nugvnfi",
    "numtpwl",
    "numaoy7",
    "nuk0fa8",
    "nuhrcys",
    "nujdoh3",
    "nuame34",
    "nuh99td",
    "nugp4rd",
    "nul44xt",
    "nui8luw",
    "nuogm8v",
    "nui5x25",
    "nul11te",
    "nud6n1f",
    "nuedk7y",
    "nu91wyk",
    "nulbrwy",
    "nu4qg6m",
    "nuej3pz",
    "nupn899",
    "nuq4rw8",
    "nucddra",
    "nuftpxo",
    "nuimvem",
    "nuerqoi",
    "nuh85kg",
    "nuevx2h",
    "nur2z9m",
    "nuqthvq",
    "nunl16i",
    "nuimnaj",
    "nugh7lh",
    "nui9hik",
    "nu8na3l",
    "nu64kab",
    "nue2pk6",
    "nuai2wy",
    "num5paw",
    "nuldj2h",
    "nuauzwy",
    "nugq7vn",
    "nuhbjxk",
    "nu7rqeh",
    "nug3ius",
    "nud7p8l",
    "nue2x9q",
    "nule1xd",
    "nulgyvs",
    "nuf2h5p",
    "nuhz6kn",
    "nullana",
    "nulpwsf",
    "numq92b",
    "nudp1kk",
    "nuichza",
    "nuluzkc",
    "nufnl7v",
    "nuh4m4y",
    "nu9urdr",
    "nugs20u",
    "numws38",
    "nuntkc7",
    "nua4qbe",
    "nuhq5ab",
    "nuoh176",
    "nup9n6p",
    "nudl97e",
    "nukq27s",
    "nuk0foy",
    "nulgscq",
    "nuhuh9v",
    "nujpdz1",
    "nu8gmdd",
    "nuhsxbr",
    "nue3pr8",
    "nunq804",
    "nuly2ew",
    "nuok1kf",
    "nu9iyhe",
    "nul0cbo",
    "nukt9pv",
    "nuikrgr",
    "nuowlgu",
    "nucypyq",
    "nudllso",
    "nud8nax",
    "nue9gxf",
    "nu9ii4d",
    "nuhajmf",
    "nupnapw",
    "nuhq7yl",
    "nukh223",
    "nueee8m",
    "nuqw4km",
    "nu8i7bu",
    "nuopb1m",
    "nudtg4q",
    "nuodda8",
    "nu5owtt",
    "nupdtb0",
    "nuoyr27",
    "nulbwt8",
    "nudz5zs",
    "numove7",
    "nuizv5q",
    "nufeusd",
    "nuer7ax",
    "nulhhet",
    "nulu7nr",
    "nuff1e4",
    "nucms3s",
    "nuomih3",
    "nudqvks",
    "nui9luv",
    "nujynz0",
    "nuod81k",
    "nunxuly",
    "nufw6ah",
    "nupd7c9",
    "nuey3a1",
    "nunko06",
    "nuiiggz",
    "nukq7ym",
    "nujcmwb",
    "nums70x",
    "nukj7xj",
    "nufumrk",
    "num8n5b",
    "nui2yak",
    "nujx801",
    "nuonqa9",
    "nukb6e1",
    "nuiq6cb",
    "nudkr3n",
    "nu5b0ci",
    "nul2coh",
    "nufoiac",
    "nudy6yn",
    "nue7lmy",
    "numt8zo",
    "nuq49pb",
    "nuhsh02",
    "nue7k5h",
    "nu56em5",
    "nud7x5j",
    "nuia04p",
    "numi9b0",
    "nue5yxb",
    "nul9b46",
    "nuivccp",
    "nuf1ib0",
    "nu52zes",
    "nubu34c",
    "nuensw3",
    "nule8hy",
    "nulqi7n",
    "nu4mbh4",
    "nun1qs1",
    "nuky3o9",
    "nuqscyq",
    "nui7mya",
    "nujheln",
    "nulqffc",
    "nufie5j",
    "nuf8akl",
    "nuc6ctv",
    "nuicf6p",
    "nujs31g",
    "nukr3o6",
    "nuel0oj",
    "numq8mv",
    "nudisyh",
    "nugzifs",
    "numtszy",
    "nudrapa",
    "numjfkl",
    "nums5uh",
    "nugs957",
    "num39tr",
    "nu4v0lj",
    "nuff4r2",
    "nuqn1zl",
    "nunb0wm",
    "nuidbal",
    "nuelorc",
    "nukng2p",
    "nu5feso",
    "nufadep",
    "nujkskk",
    "nud80su",
    "nums25g",
    "nufayu3",
    "numa0ie",
    "nuhht41",
    "nu8txui",
    "nuldusd",
    "nufdmbi",
    "nuhs5ps",
    "nuettzb",
    "nuldhio",
    "numumvm",
    "numc0fu",
    "nuod6vl",
    "nuk0ns9",
    "nu9skrr",
    "nulo7om",
    "nundlva",
    "nu5wc9z",
    "nuekig3",
    "nukaq2n",
    "numi1cc",
    "nukrqe5",
    "nu969dc",
    "nuj2nft",
    "nuglyja",
    "nu52co2",
    "nup1ixi",
    "nuk1aw6",
    "nuq67i2",
    "nugl66c",
    "nuh6acv",
    "nuhxfsu",
    "nu5tcav",
    "nuozaew",
    "nulb2n3",
    "nufc6yd",
    "nu91i4i",
    "nujkoz5",
    "nuktobs",
    "nu4oedy",
    "nu9shau",
    "nup0pq1",
    "nufllv1",
    "nugabq6",
    "nuejvjv",
    "nuntyd2",
    "nuljts1",
    "nufh4rr",
    "nue00ow",
    "nuiywl4",
    "nunoxc6",
    "nud27aa",
    "nueu7ul",
    "nudycmn",
    "nuknwej",
    "nuewdzw",
    "nud8ib4",
    "nudmnpo",
    "nufh49d",
    "nuis4oc",
    "nunpi71",
    "nujy6c8",
    "nuh9j2x",
    "nudke5d",
    "nueumpp",
    "numl5yf",
    "nughkm6",
    "nufj88p",
    "nuqprgp",
    "nu8gldw",
    "nuley6u",
    "nuedzr9",
    "nuhsepx",
    "nuatz2k",
    "nulecao",
    "nulds8z",
    "nuccisj",
    "nul1uov",
    "nue392q",
    "nup02bj",
    "nujqsjr",
    "nu6sj4i",
    "nuliivr",
    "nulx84k",
    "nuknl69",
    "nugk2l6",
    "nul75aa",
    "nu5l588",
    "nulm1dq",
    "nu69gqw",
    "nukr9hv",
    "nuhwjzo",
    "nue9tup",
    "nu7ugcd",
    "nuearum",
    "nuhedc9",
    "nu4zlq3",
    "numrv7j",
    "nudrzaq",
    "nudeb4y",
    "nu9spm7",
    "numr1ll",
    "nufqnup",
    "nu63kbo",
    "nuis8kv",
    "nudjsue",
    "nuksmvx",
    "numti9u",
    "nujp7vy",
    "nud5vvg",
    "nuipxb3",
    "nuphhv4",
    "nukooa9",
    "nugw1xw",
    "nuoddbm",
    "nuk5b7e",
    "nulr39c",
    "nu54aj7",
    "nugpys0",
    "nucuvdu",
    "nupzjml",
    "nuikwul",
    "nu4qw0h",
    "nucpyin",
    "nuia4sl",
    "nuqv9eu",
    "numtuo1",
    "nuf5lol",
    "nupujrv",
    "nuosv3f",
    "nud1q6a",
    "nuko5d0",
    "nukimvb",
    "nu852k7",
    "nuf8osx",
    "nuah2r7",
    "nubx67f",
    "nukbh71",
    "numyljk",
    "nunckgo",
    "nul7e4e",
    "nul620u",
    "nuea1wy",
    "nup96mw",
    "nue9xby",
    "nuhtbp4",
    "nun5ma9",
    "nuj0y1d",
    "num154e",
    "nu9xgb7",
    "nudtmd6",
    "nunwdbu",
    "nufahcy",
    "nu94for",
    "nu7lmgz",
    "nupdxur",
    "nufaqbh",
    "nu5w59t",
    "nuh9smy",
    "nuj75lm",
    "nualq6v",
    "nu71lp6",
    "numzz9x",
    "nuli2y3",
    "nummh2f",
    "nunlxxu",
    "nulpnd8",
    "nuegc9w",
    "nufkezj",
    "nuglk8n",
    "nuekl3x",
    "nugwm88",
    "nujkfgl",
    "nuetagi",
    "nul6b8b",
    "nui3awl",
    "nufwomh",
    "nuok81v",
    "nugvg8e",
    "numv0jh",
    "nulnfji",
    "nujsk0k",
    "nug3x24",
    "nu5zpdx",
    "nufoxyd",
    "nul5b61",
    "nu967f4",
    "nud4a7v",
    "nukbjl5",
    "nucd5iq",
    "nuj8bu3",
    "nuj5780",
    "nulqqs4",
    "nuja9ct",
    "nuoxz6h",
    "nupfje8",
    "nuj8eif",
    "nulk8mv",
    "nu4jrzt",
    "nun86nt",
    "nuieoyt",
    "nuo2jki",
    "nujbw5d",
    "nuoysfa",
    "nuhriw8",
    "nu7kzwx",
    "nuikkst",
    "nuci12s",
    "nu57ga0",
    "nua095q",
    "nuin14z",
    "nufdxsk",
    "nufgaog",
    "nugfg4l",
    "nug403r",
    "nujnf56",
    "nukscyb",
    "nunpvpy",
    "nu9yzq7",
    "nue5n31",
    "nu5u4m3",
    "nufrni4",
    "nukd2jy",
    "num46f5",
    "nueiank",
    "nujgnoe",
    "nunzamo",
    "nuew898",
    "numjblb",
    "nugrrt3",
    "numu5ia",
    "nuo68er",
    "nu6mg7j",
    "nuqtwiq",
    "nu85avd",
    "nulwk3i",
    "nuir4ed",
    "nul83uj",
    "nuhfeqw",
    "nu9ng62",
    "nuql7nq",
    "nuieo8x",
    "nufbvtz",
    "nuk0z0q",
    "nuhnx5z",
    "nu9ufvw",
    "nup9wyk",
    "nupfoa8",
    "nulhj8u",
    "nukosh1",
    "nufh5m0",
    "nufcw1m",
    "nu7n8vz",
    "nuf4znc",
    "nuid838",
    "nulfpxy",
    "nuidzbm",
    "nu7dvpy",
    "nuaodc7",
    "nuhxyml",
    "nul0o1j",
    "nucresb",
    "num7iof",
    "numdqsv",
    "nukolpp",
    "nudz6an",
    "nuj345y",
    "nue7rdj",
    "nucsn13",
    "nup79sk",
    "nudzlaz",
    "nuelaum",
    "nu5vict",
    "nupgpg5",
    "nue6c2a",
    "nubbpl6",
    "nuiy582",
    "nu56tvc",
    "nuh3srk",
    "nueuubw",
    "nuo3fs7",
    "nu7ctlp",
    "nun6doy",
    "nujgi6c",
    "nul8jyc",
    "nukgfy2",
    "nuio7k9",
    "nuehooh",
    "numu6s8",
    "num0x2e",
    "nu9mce4",
    "nue4gg3",
    "nujgayh",
    "nule5hx",
    "nu7v23x",
    "numpsho",
    "nudz6tr",
    "nukhy8m",
    "nubkfd5",
    "nupitp1",
    "nu6ok9s",
    "nu6tfh9",
    "nujsl4w",
    "nuk0vs9",
    "nunljq9",
    "nua9wb7",
    "nuoxqak",
    "nuecrp2",
    "nuirta2",
    "nufeka9",
    "nuhrvtp",
    "nu4cuvf",
    "nufn9vl",
    "nulh22t",
    "nuek52q",
    "nuljydb",
    "nugnsgm",
    "nujnjm0",
    "nuaym6n",
    "nue4rm2",
    "nuk19gl",
    "nu6rpmf",
    "nuerzpu",
    "nunruf9",
    "nun815q",
    "nud2khm",
    "numjhtl",
    "nuavxt0",
    "nui9x9k",
    "nujbo3l",
    "nur0gx1",
    "nuqjgl3",
    "nujejf7",
    "nukwap2",
    "nu7svg4",
    "nupd0b8",
    "nuiskjq",
    "nuf9an9",
    "nueb2j5",
    "nupjre7",
    "num66qd",
    "nuqvkv3",
    "nueris0",
    "nulpysu",
    "numw91x",
    "nur0nw0",
    "nud7uj3",
    "nuinu0a",
    "nubyqi7",
    "nue9rbm",
    "nuelo4a",
    "nun68bv",
    "nukv1xm",
    "nuq7af6",
    "numrw7o",
    "nu9qn4c",
    "nuncel9",
    "nugklah",
    "nudax18",
    "nuaus7j",
    "nujx2du",
    "numgnqx",
    "nukza08",
    "nul4iyp",
    "nuk0cta",
    "nuppkfa",
    "nuo1nh3",
    "nupvxsf",
    "nue3kme",
    "nunvuxf",
    "nuph3gd",
    "nud9dhq",
    "nuorjje",
    "nunu3f0",
    "nuiiqi7",
    "nuqgejj",
    "nulu7ni",
    "nulmjmi",
    "num9d50",
    "nul9vgg",
    "nukvyke",
    "nunb2ty",
    "nujnien",
    "nuhtjvy",
    "nucgz3p",
    "nu6na18",
    "nuehluq",
    "num8mui",
    "nuiwy5i",
    "nuewtb5",
    "nuhrh5x",
    "nudrde2",
    "nul2y8k",
    "nug1ykz",
    "nukxlba",
    "nujwj3v",
    "nupy7ua",
    "nuflrj0",
    "nul013w",
    "numyahh",
    "num17kx",
    "nupr6qq",
    "nuigmyu",
    "nu4a17f",
    "nuehvtc",
    "nulexyk",
    "numpic7",
    "nuo6gc4",
    "nuoj1ot",
    "nujfopt",
    "nukzy6n",
    "nu5griq",
    "nu5m35y",
    "nuelwj7",
    "nu9cxd6",
    "nugeacz",
    "nul8yac",
    "nupt4b9",
    "nunm1iq",
    "nujpy9d",
    "nuf8p9u",
    "nujkcoc",
    "nupp9rs",
    "nuog88q",
    "nuhcwb9",
    "nujp3oz",
    "nuadzms",
    "nulswo9",
    "nuli9u6",
    "num98a9",
    "nue1as8",
    "nulfc8b",
    "nudw4vm",
    "nuhg9n8",
    "nu4o74h",
    "nudgdcl",
    "nu6ui2p",
    "nuojiwu",
    "nuklta4",
    "nucgj5e",
    "nuewkqq",
    "nufow9a",
    "nueiswl",
    "nuiquvz",
    "nul8sf3",
    "nudevmy",
    "nunj4gj",
    "nulk6fr",
    "nuj8hkd",
    "nu4i9ue",
    "nuibpjf",
    "nua5isu",
    "nuf5yml",
    "nuk10uy",
    "nub7dro",
    "nuphbu5",
    "nupywxp",
    "nu4auhg",
    "nugsjy0",
    "nuko836",
    "nufixqg",
    "nupigb7",
    "nul7tbo",
    "nuovo9n",
    "nuo833z",
    "num2ow1",
    "nub6pft",
    "nujdvxf",
    "nuet83h",
    "nub1t9v",
    "nu9zz9q",
    "nunj5wf",
    "nuqsozh",
    "nueo4g9",
    "nuedp2b",
    "nuia57b",
    "nunpacz",
    "nujghk1",
    "nuo7woo",
    "nuonr7i",
    "nuefkic",
    "nuja2e4",
    "nu7qzgf",
    "nu7l6ry",
    "nuhfeq7",
    "nuijq5i",
    "nuirow2",
    "nukvlga",
    "nuapy63",
    "nuh418u",
    "nuea0u9",
    "nujfuca",
    "nuik7vx",
    "nue306d",
    "nuqufh4",
    "nue1msu",
    "nup27hh",
    "nuk08fw",
    "nuimjjx",
    "nugnopl",
    "numo25j",
    "nulh0te",
    "nuilyxc",
    "nuluecx",
    "nupuddy",
    "nu4ipu8",
    "nueepgw",
    "nujm4l4",
    "nuieyqw",
    "nuiiyeb",
    "nup7xl1",
    "nuincen",
    "nudj9qv",
    "nul2ws5",
    "nukpyx0",
    "nuiw5q9",
    "nueinch",
    "nuirooi",
    "numedmz",
    "nukdqs7",
    "nulfwxo",
    "nupujzy",
    "nug5ko0",
    "nul767p",
    "nui3bpx",
    "nu84ff7",
    "numsc8t",
    "nugyj7r",
    "nu8ob82",
    "nucmg9d",
    "nuj8zb7",
    "nu6282z",
    "nugxmyl",
    "nua3taf",
    "nuicn8g",
    "nu4h0gu",
    "nu6syv5",
    "nugdrl8",
    "nuomzpj",
    "nuepfkx",
    "numqs5s",
    "nu4kh60",
    "nu4knya",
    "numq51p",
    "nuhpsud",
    "nubtend",
    "nunbo46",
    "nuglhfh",
    "nufo98q",
    "nuewte2",
    "nu8qovd",
    "nuhbj15",
    "numrz8m",
    "nugzg9q",
    "numfn9r",
    "nukrfk0",
    "nu6aday",
    "numes0y",
    "nugvgk0",
    "nu9vip0",
    "numcy9k",
    "nujn5gb",
    "nufnw1i",
    "nulx4i2",
    "nuigtci",
    "nud7f2h",
    "nup467z",
    "nu4gixd",
    "nua4xph",
    "nu9nsk5",
    "nufm2x1",
    "numnx6t",
    "nuc9xnr",
    "nuehtxi",
    "nu5s000",
    "nu96gur",
    "nu8q78l",
    "nu9qmye",
    "nuj0xiv",
    "nufx59n",
    "nul3w94",
    "nukpjw0",
    "nu6xcwn",
    "nuogme9",
    "nujx6kw",
    "nukcx23",
    "nuiumzb",
    "nul1lbn",
    "nuhzvd1",
    "nupinlo",
    "nudaqqw",
    "nuois4x",
    "nu9mouk",
    "nupu9e7",
    "num2r3x",
    "nu95zxs",
    "nul8w6v",
    "nue5qkl",
    "nui0qb4",
    "nuf1cm5",
    "nulxzgp",
    "nuknpt0",
    "nukywnv",
    "nuk0qq3",
    "nunqntw",
    "nuoj3hg",
    "nulh2c1",
    "nuc4r19",
    "nujw4ff",
    "nufknzv",
    "nuie5rc",
    "nucyhdl",
    "nue0d80",
    "nupyvgh",
    "nuk0qq6",
    "nul23o3",
    "nuebke9",
    "nujt42t",
    "nuoif6k",
    "nukndrj",
    "nuq9sk8",
    "nu5vilf",
    "nukxy0q",
    "nugv9d3",
    "nuf3lee",
    "nuqp96z",
    "nulv5cw",
    "nu4re25",
    "nue9nt0",
    "nuiji1x",
    "nufoiei",
    "nu9fp8u",
    "nu5rrzu",
    "nu9ktzj",
    "nujlofg",
    "nuoqf59",
    "nul7rqo",
    "nujdvml",
    "nuk4s6i",
    "nuci0w1",
    "nuejp1t",
    "nuogokj",
    "nuidyu3",
    "nuh15u5",
    "nu9rvkv",
    "nui7trg",
    "nupt0zh",
    "nukqhcb",
    "nulgdda",
    "nuld6t3",
    "nul838a",
    "nugwc4h",
    "nulroxp",
    "nuqb9o4",
    "nucl2ye",
    "nuiys12",
    "nuez3i0",
    "nu9lvz1",
    "nu8s768",
    "nuln9eq",
    "nukp9n0",
    "nult7d7",
    "nulrff0",
    "nue7cci",
    "nuinhs1",
    "nunbtiv",
    "nud7im0",
    "nunjwu1",
    "nudzgdo",
    "nuojeq5",
    "nuorasu",
    "nudx8w0",
    "nuefqpe",
    "nujwzn7",
    "nuj3g9s",
    "nujtxlu",
    "numuer0",
    "nub1m3r",
    "nup1vfa",
    "nu9xf9x",
    "nu9zxsw",
    "nu6d9fs",
    "nui109s",
    "nudpmxo",
    "nuej9pb",
    "nuon96u",
    "nug053l",
    "nujy8zi",
    "nu9ne75",
    "nue5584",
    "nul824z",
    "nulf1qf",
    "nudjd35",
    "nul6fu1",
    "nuh7wa1",
    "nu5dil4",
    "nuknr1x",
    "nuq6g69",
    "nujafgf",
    "num1v6i",
    "nuga17o",
    "nucreg8",
    "nukrndt",
    "nunygxg",
    "nuk6mcf",
    "nukgb8o",
    "nun08pi",
    "nukogpf",
    "nu9vnb0",
    "nui8doq",
    "nufiqdp",
    "numa7kw",
    "nup38nb",
    "nunlxz2",
    "nulo6b3",
    "nuf9xrz",
    "nuoqtam",
    "num5tbi",
    "nukvqx3",
    "nukr5w0",
    "nugwfzm",
    "nu9djsa",
    "nufn2up",
    "nup8aed",
    "nupu65i",
    "nudk4eu",
    "nu9auk7",
    "nugzm3a",
    "nuptakg",
    "nulgvj9",
    "nukf181",
    "nukkv83",
    "nu8y3qb",
    "nu81n9a",
    "nu6rlqd",
    "nu7yj2n",
    "nuczaly",
    "num3tyc",
    "nu6assm",
    "nupkhn9",
    "nups9em",
    "nugpfm4",
    "nulhk7c",
    "nul6h57",
    "nujclh2",
    "nuigj70",
    "nudp6by",
    "nug1rvb",
    "nun47fe",
    "nu8x2sq",
    "nuefr2p",
    "nud22f5",
    "nu560l9",
    "nujx0fc",
    "nueb187",
    "nui717g",
    "nu6nfwx",
    "nujjrin",
    "nupg3ne",
    "nufutp5",
    "num1i3a",
    "nue7xn2",
    "nu58k6h",
    "nuifinl",
    "nuls45q",
    "nuplvf2",
    "nueqsi1",
    "nu6x5z0",
    "nuoiatj",
    "nuivhob",
    "nufyyk6",
    "nun49is",
    "nue2kax",
    "nuo4nix",
    "nuourfb",
    "nulm724",
    "nueegev",
    "nuedcar",
    "num9net",
    "nugxwvy",
    "num6t3c",
    "nuiehmw",
    "nuipu6f",
    "nufseb3",
    "nuin4d6",
    "nulqodm",
    "nupxaue",
    "nuks7uh",
    "nuj7dwb",
    "nuea35x",
    "nuiavrg",
    "nu9pfmf",
    "nug9uu5",
    "nul8eco",
    "nuefor5",
    "nuk70hw",
    "nucyfom",
    "nupi1z9",
    "nu9fou9",
    "nuehfb7",
    "nufmg04",
    "nuq2c0z",
    "num987t",
    "numq25a",
    "nujg5hj",
    "nua61ps",
    "nuac73i",
    "nujbv9y",
    "nuk1phn",
    "nu9ngfi",
    "nudns67",
    "nuq5dc8",
    "nu96xzx",
    "nupdlb2",
    "nu9pex9",
    "nu5lanx",
    "nuo2s37",
    "nu70ud2",
    "nuk1tcu",
    "nujlju8",
    "nudufng",
    "nufl2fg",
    "nuo4qrv",
    "nuc8eb9",
    "nuhngq1",
    "nun4wle",
    "nui50fd",
    "nupvnjs",
    "nu82wek",
    "nufa6gd",
    "nuhm17h",
    "nuebp4i",
    "nupx83m",
    "nu4rjqj",
    "nuqwvge",
    "nu4rneh",
    "nui3x5k",
    "nu54es0",
    "nudx28a",
    "nujwdil",
    "nuisepf",
    "nugdylp",
    "nueu2j7",
    "nujjl5k",
    "nukd6ou",
    "nuiaswz",
    "nupd4rz",
    "nu721n9",
    "nudxqdn",
    "nuibyec",
    "nuksnlx",
    "nuecmz4",
    "nulrpj8",
    "nu9wcm7",
    "nujfv6h",
    "nul2tib",
    "nuksenx",
    "nuhu72z",
    "nulhkjm",
    "nuex3iz",
    "nuojxdd",
    "nueaui1",
    "nujw8o0",
    "nujo8lh",
    "nujoeci",
    "nukws68",
    "nundlzi",
    "nuhk3p5",
    "nuljmlx",
    "nukrqnn",
    "nun6dih",
    "nunevyo",
    "nui0wfk",
    "nui1a59",
    "nujg3gz",
    "nup60vb",
    "nujvxoj",
    "nu79mg8",
    "nufp40w",
    "nulw5s8",
    "nufqtdj",
    "nueyl2d",
    "nugli6g",
    "nu8ljf0",
    "nujzppo",
    "nujox91",
    "nuo3nz8",
    "nuguq7m",
    "nudozkh",
    "nukxl0w",
    "nujaldf",
    "nuh50qt",
    "nuhp4q4",
    "nukm17p",
    "nui7oot",
    "nucm4hx",
    "nunbqx2",
    "nuklxw4",
    "nufl5w5",
    "nufz9j3",
    "nuabwzm",
    "nuhcjbw",
    "nue5r58",
    "nuj5j8r",
    "nujmmn6",
    "nuc6dxs",
    "nueucau",
    "nukad9n",
    "nuf7559",
    "nu9n809",
    "nujvypc",
    "nufhnhg",
    "nulyxao",
    "nu4qicv",
    "nui8uyv",
    "nugejgz",
    "nu727xd",
    "nulfpww",
    "nuem2hq",
    "nubrocv",
    "nugy3ay",
    "nu9blte",
    "nup9jr4",
    "nuh9eh7",
    "nuo8l5y",
    "nuljydw",
    "nuekkqh",
    "num0uf1",
    "nu9yi0w",
    "nu98rwp",
    "nuk0zrv",
    "nujb1a5",
    "nu9dd6h",
    "num1ryg",
    "nuhrkyw",
    "numfm7i",
    "nupx86l",
    "nuf730w",
    "nuq71bg",
    "numa3v3",
    "nu63btz",
    "nuiqids",
    "nufnb5y",
    "nuijbgv",
    "nukz7pi",
    "nuctat0",
    "nuh5wld",
    "nuh2749",
    "nujybjr",
    "nul6nrz",
    "nu7dt3t",
    "nuh5e3n",
    "nuk7458",
    "nupzsjq",
    "nu8611z",
    "nuelws0",
    "nud5do0",
    "nu9ywd1",
    "nudr0yk",
    "nulcvqb",
    "nu5h4ex",
    "nuc1d55",
    "nufzy72",
    "nuaocbf",
    "num3zzo",
    "nuj776m",
    "nukmbyq",
    "nuipw1z",
    "nucj25n",
    "nue0x98",
    "nu9cvk1",
    "nuatk63",
    "nug77ib",
    "nuprpan",
    "nu7vp1w",
    "nuokc50",
    "nuojzq2",
    "nugxhll",
    "nuac7ce",
    "numqv2h",
    "nudewdz",
    "nui4m87",
    "nu8xerv",
    "nuisgxc",
    "nuls6gw",
    "nuee2iy",
    "nufn0hm",
    "nuguw30",
    "nulx1qx",
    "nuhq3hp",
    "nughq9l",
    "nueuz6m",
    "nua52g4",
    "nuhqv5m",
    "nuohqio",
    "nul4mku",
    "nue9f1j",
    "nu6i6md",
    "nu4oz03",
    "nubahsk",
    "numvljt",
    "nul4ndm",
    "nuhos49",
    "nuczyre",
    "nuecn1y",
    "nulbsnk",
    "nuq12vv",
    "nuo9zwz",
    "nu5wmfu",
    "nuf7bq3",
    "nueuvgu",
    "nufwoce",
    "nueoauz",
    "nupv9gc",
    "nuoczvg",
    "nufjqv0",
    "nudkqex",
    "nud4ayi",
    "nueb3jh",
    "nuktxl1",
    "nukrpi2",
    "nu5f0sg",
    "nui00iy",
    "nugawyc",
    "nufr4yv",
    "nukodni",
    "nug2q8o",
    "nulkzmk",
    "nug1xmi",
    "nul2q1x",
    "nupasgw",
    "nueuk7n",
    "nuioi88",
    "nup6nat",
    "nuffdtb",
    "nu5qb41",
    "nuep2p4",
    "nu8qech",
    "nu6vyva",
    "nug2ej2",
    "nu9sul9",
    "nuhy2ob",
    "nupporl",
    "nuks3a3",
    "nuhykhi",
    "nu6xnws",
    "nue94eh",
    "nukvsug",
    "nuoi3l8",
    "nufjzlq",
    "nuitsre",
    "nu4jky2",
    "nuem2d5",
    "nulyei3",
    "nucaqr0",
    "numsw1t",
    "nue9azi",
    "nuirjoq",
    "nuavy8n",
    "nuina7g",
    "nui7nvb",
    "nu593ur",
    "nukp32z",
    "nuadvfx",
    "nuahp83",
    "nuduwc5",
    "nult4uu",
    "num0hkd",
    "numoeou",
    "nucgxyw",
    "nukthz2",
    "nu49oh4",
    "numdg3l",
    "nullxn3",
    "nuhg3e9",
    "nue0omv",
    "nukjwzt",
    "nu7vo0m",
    "nuj4784",
    "nu5r1rp",
    "nul6zsq",
    "nuqtixp",
    "nunz8yk",
    "nui10w2",
    "nufl7ki",
    "nuejyfa",
    "nuh6tci",
    "nuj9mzk",
    "nupgfts",
    "nujuesz",
    "nu6g6lh",
    "nugl6h7",
    "nuhgqsn",
    "nujdfxp",
    "nub3nxp",
    "nug7lf1",
    "nueuc3s",
    "nuk3p2h",
    "nufmtho",
    "nul081i",
    "nufy56e",
    "nuj85e3",
    "nulnlw9",
    "nujzyo1",
    "nuinrxm",
    "nuevpv6",
    "nu5p1n9",
    "nuaot3k",
    "nud78lc",
    "nujpob4",
    "numpnd5",
    "nuktbt9",
    "nu5bt0c",
    "nui9p4h",
    "nun2hyj",
    "nu7vc0f",
    "nuj760s",
    "nujq7q3",
    "nunua6a",
    "nu4wds9",
    "nu86ur8",
    "nujwtxf",
    "nuein7t",
    "numnlw4",
    "nuebg1m",
    "nue5sex",
    "nun59mg",
    "nufanea",
    "nulay4u",
    "nuixt3o",
    "nuhm0zp",
    "nuk1cw5",
    "nukttm2",
    "nuew82i",
    "nuecgps",
    "nukwwop",
    "nujgvtm",
    "nu97iwb",
    "nultapm",
    "nuijqwx",
    "nuedbr4",
    "nuqtgux",
    "nuk40zg",
    "nuk80ud",
    "nujifbf",
    "nu6fzzf",
    "nue6qxy",
    "nujxb7k",
    "nulgd2i",
    "nuka7f4",
    "nu9zhwd",
    "nupcuut",
    "nubmkrz",
    "nuill7f",
    "nuht5wt",
    "nudyln2",
    "nupfswu",
    "nufmg7v",
    "nul30ns",
    "nuke0vn",
    "nuqi0mp",
    "nulv0ax",
    "nu9nyat",
    "nuo39ps",
    "nupkvvv",
    "nunx6vj",
    "numo43e",
    "nujc0vz",
    "nuidjm2",
    "nuq7tg7",
    "nudl7xh",
    "nujui9t",
    "nuf5npy",
    "nujt8s3",
    "nu6slyd",
    "nuhciqv",
    "nudyb2a",
    "nuldi3r",
    "nuia239",
    "nur36kz",
    "nujeiq6",
    "nuefnmo",
    "nulth8q",
    "nuovrvk",
    "nu7rfrl",
    "nufcqxh",
    "nupfrj4",
    "nue4wta",
    "nuadiyg",
    "nuq75eg",
    "nua7rvu",
    "numv92t",
    "nu6e7a5",
    "nudg506",
    "nupg36l",
    "nuju9jd",
    "nujpmah",
    "nugerl3",
    "nupemk7",
    "nunwlxl",
    "nuh66da",
    "nuqpjg6",
    "numjanh",
    "nudpeq9",
    "nujrb4c",
    "nuj5elv",
    "nudwzap",
    "nujyiag",
    "nujx0un",
    "nucr7qg",
    "nufp1tz",
    "nupi8tp",
    "nuiwoo5",
    "nu76z6q",
    "nuhowo9",
    "numxgkb",
    "nuadlk9",
    "nu8aqoz",
    "nuqsoru",
    "nukovh0",
    "nubr1a7",
    "numsrkl",
    "nuk3279",
    "nuexste",
    "nuf5t6q",
    "nuf2zgj",
    "nunnqaz",
    "nu5h3h8",
    "nuqhlg7",
    "nuplnvs",
    "nupsow7",
    "nu98iu8",
    "nu4j3a7",
    "nufmltm",
    "nu5hsc9",
    "nu6suzd",
    "nu5zoaq",
    "nuljhmv",
    "nugdlnt",
    "nukt08g",
    "nuenauf",
    "nu5xa8x",
    "nulsqhw",
    "nudm9ao",
    "nupehoz",
    "nuknzew",
    "nudf6dv",
    "nupqj12",
    "nueluq6",
    "nujfih5",
    "nuk9ox6",
    "nui93kl",
    "nukwywh",
    "nulxme4",
    "nul3472",
    "nufr53g",
    "numgkcp",
    "nufkg20",
    "nuqqvon",
    "nufc5jd",
    "nue22ms",
    "nuaq4ne",
    "nupf25g",
    "nuhac53",
    "nul9xyt",
    "nudxzrq",
    "numcods",
    "nuknvwf",
    "nujdidf",
    "nuaec69",
    "nukafij",
    "nule1zq",
    "nupvrdj",
    "nudkgug",
    "nuk2dij",
    "nuqcjv2",
    "numqcgv",
    "nuiftx0",
    "nufoewh",
    "nukonwq",
    "nulmfwz",
    "nug7b6g",
    "nukzf13",
    "nufmbqt",
    "nuh5osi",
    "nuqqi1t",
    "nui1bla",
    "nuf6z35",
    "nuodtwl",
    "nu9ciyw",
    "nu55u8l",
    "nummen3",
    "nu5em8i",
    "nuj0ivu",
    "nuftrzu",
    "nuk8hgg",
    "nu4d4j1",
    "nu89oqt",
    "nufleqt",
    "nudkrmu",
    "nuh2e26",
    "nu9d0uc",
    "nul2ac1",
    "nukkfjj",
    "nu5hrj4",
    "nul5qil",
    "num0eni",
    "nud41ke",
    "nujxuzc",
    "nubs2bp",
    "nun7pba",
    "nuizt3w",
    "nul4wy0",
    "nu5bnef",
    "nuh9w5y",
    "nulmlnu",
    "nulhe20",
    "nufyc6w",
    "nu58k5v",
    "nui9ois",
    "nulni1x",
    "nudk39y",
    "numt4pu",
    "nul25rp",
    "nufulbf",
    "nu9z9sb",
    "numf3zu",
    "nu9wpoo",
    "nu4d10w",
    "nu5kn21",
    "nulv6yv",
    "nujuie1",
    "nugfcsl",
    "nufhiwj",
    "nuhrgfs",
    "nulxzr2",
    "nuip4hs",
    "nujnzml",
    "nu6z24a",
    "nuczz4u",
    "nufzt5c",
    "nu8w7vb",
    "nuic1ow",
    "nu51w8t",
    "nu4ieac",
    "nu74u4r",
    "nuie326",
    "nupcszp",
    "nugqip1",
    "nupywxk",
    "nu980g1",
    "nuhxuwx",
    "nuew1wo",
    "numw6zn",
    "nudroy6",
    "nuksze4",
    "nuenpvg",
    "nuhfveb",
    "nupnlmf",
    "nudo4ff",
    "nuf2gaj",
    "nufeifj",
    "nue3juf",
    "numrul9",
    "nuicc57",
    "nu538ko",
    "nudvpp9",
    "nuikghw",
    "nug1z67",
    "nue4j6b",
    "nueh0aq",
    "nukp7zz",
    "nuosgun",
    "nu8uzbp",
    "nul4zlp",
    "nuot22h",
    "nujk3v7",
    "nukurzf",
    "nuehuux",
    "numdddt",
    "nu9orbj",
    "nucqolu",
    "nuqxhvt",
    "nuj7qih",
    "nug31yk",
    "nugnboh",
    "nune4qs",
    "nui168b",
    "nuoepus",
    "nuho44k",
    "num5hev",
    "nun0nd7",
    "nulxq24",
    "nuljbe8",
    "nuozi83",
    "nuhfwdd",
    "nuage22",
    "nujknc7",
    "nudxml0",
    "nun55la",
    "nu56z8y",
    "nufr01i",
    "nu6try2",
    "nulp1u9",
    "nueesrb",
    "nul8cqr",
    "nueejlu",
    "nuelkrz",
    "nue1xwp",
    "nufsjnx",
    "nul8kn2",
    "nu7t49t",
    "nuqvi47",
    "nujb6qt",
    "nu5bgw5",
    "nugy1be",
    "nub5r86",
    "nul2v1p",
    "nuk4s76",
    "nuf6n5c",
    "nupk9i6",
    "nuoap46",
    "nu4clf2",
    "nulcukq",
    "nuohxqe",
    "nufu44b",
    "nufqfuh",
    "nud1tdi",
    "nuk8uwk",
    "nufg5zl",
    "numvlbr",
    "nue72mi",
    "nul66qr",
    "nud52gm",
    "nuijfzh",
    "nup7l7y",
    "nua5c0h",
    "nul8q94",
    "nulee64",
    "nujwvzv",
    "nuo20g7",
    "nucbyw8",
    "nubs23m",
    "nukoqdj",
    "nuf0yu5",
    "nu8b100",
    "nuku4vw",
    "nuh0mtb",
    "nunbgoo",
    "nujs6rm",
    "nujzcgm",
    "nu52p0w",
    "nulaiua",
    "nud14ls",
    "nua7bci",
    "nuf6bca",
    "nuktqdj",
    "numqg87",
    "nu5u9of",
    "nua3wa7",
    "nudzhv2",
    "nulbqag",
    "nunutq8",
    "nuafvra",
    "nuoey4j",
    "nu71q8i",
    "nuif1ye",
    "nuegz2b",
    "nudpet2",
    "nuph4d1",
    "nu8izew",
    "nue5zke",
    "numnjkr",
    "nul3dip",
    "nufw2rq",
    "nujqw5u",
    "nu9t949",
    "nuhpves",
    "nubbhc1",
    "nufw82g",
    "nuejax4",
    "nubeqba",
    "nulg3tr",
    "nuld83y",
    "nul8anq",
    "nuei29y",
    "nuis8js",
    "nulps4o",
    "nu7kuvn",
    "nuc5vmx",
    "nueucgq",
    "numpu7y",
    "nugjjm9",
    "nukgqgg",
    "nuf6ce5",
    "nu4g0zb",
    "nuq8w0o",
    "nuopzwo",
    "nuq1v0r",
    "nugpnua",
    "nuh92sq",
    "nuk3lf0",
    "nub8dwt",
    "numt9o9",
    "nudz2s1",
    "nu9y4jr",
    "nuk8pih",
    "nund02n",
    "nuhuzuz",
    "nuj7aoj",
    "nulfd3i",
    "nupv2xf",
    "nul7few",
    "nun90wb",
    "nudku0p",
    "num6mkm",
    "nuithjb",
    "nu9qfe2",
    "nunk4km",
    "nuqh1qd",
    "nu9c14i",
    "nujhb0d",
    "nu8uhm2",
    "nuqhdzs",
    "nuisyjm",
    "nu907p6",
    "nud8sih",
    "nuevs5m",
    "nujpnom",
    "nuj36wu",
    "nult5ya",
    "nu4g6cy",
    "nue7v2v",
    "nue67q6",
    "nujbg8y",
    "nulxq4m",
    "nufefo6",
    "nukyfp3",
    "nud4obl",
    "nujtktw",
    "nulk6xx",
    "nupl73k",
    "nudx235",
    "nupg608",
    "nu7ecqc",
    "nukkey2",
    "nudibf5",
    "nuer9at",
    "nugedz8",
    "nuhx7cq",
    "nuhmf4b",
    "nul8q77",
    "nulxkcy",
    "nudxisw",
    "nu7bqk3",
    "nu6pdin",
    "nuhz2rx",
    "nuluruv",
    "nul5hkv",
    "nu69qj3",
    "nuhtc8d",
    "nul8qxk",
    "nu655vf",
    "nujf9me",
    "nukztdl",
    "nu50r0b",
    "nud08tp",
    "nuep5az",
    "nuiij1u",
    "nunphwe",
    "numa125",
    "numfgp0",
    "nu8sory",
    "nunnq3n",
    "nukbg97",
    "nu56kod",
    "nupce5x",
    "nufq7xt",
    "nue8bhi",
    "nuj5rlg",
    "nuixqwc",
    "nu5ynv0",
    "nuj1kar",
    "nuo8v23",
    "nui52c5",
    "nue81b3",
    "nuimxwg",
    "nuklqmd",
    "nufd4jj",
    "nu73ujb",
    "nujad5r",
    "nuqnguk",
    "nueuwc3",
    "nulx3p2",
    "nuoqlwi",
    "nuitnji",
    "nujxmm6",
    "nue81j7",
    "numxu4p",
    "nujgw2i",
    "nuqsrsc",
    "nuapscq",
    "nu9cpjd",
    "nugw8fv",
    "nul8h5b",
    "nukwtuf",
    "nu8xpo0",
    "nud5ny8",
    "nua331y",
    "nupn26r",
    "nuljlf3",
    "nu6d9bu",
    "nuoby8y",
    "nuiphz3",
    "nuns0yf",
    "nua0caw",
    "nuegl2w",
    "numz0q7",
    "nujnq46",
    "nu6wxhy",
    "nubri27",
    "nujswdm",
    "nu9fhfw",
    "nulivpa",
    "nuj8i45",
    "nucoe8o",
    "nuck509",
    "nueqdwv",
    "nueviis",
    "numtj1l",
    "num5tpk",
    "nuokav4",
    "nu5hikt",
    "nu66xqc",
    "nuidh8k",
    "nudjzou",
    "num694e",
    "nukal59",
    "nuqd48u",
    "numvqod",
    "nulgeqf",
    "nuc9ymp",
    "nuek6gg",
    "nudk6rk",
    "nuei0ko",
    "numti5t",
    "nuljbed",
    "nuhva29",
    "nufb5km",
    "nua76dt",
    "nudjmjz",
    "nu5gk84",
    "nupfi4u",
    "nucfoi6",
    "nulj2yw",
    "nukpts1",
    "nuljzqa",
    "numglms",
    "nuennxf",
    "nukga2t",
    "nuef3l0",
    "nul4t2c",
    "nujut13",
    "nuibv5x",
    "nu4d362",
    "nul77jh",
    "nuqt0t1",
    "nugogct",
    "nuehvsk",
    "nubxnsb",
    "nuefeni",
    "nu6ld1r",
    "nuewt2t",
    "nujat20",
    "nuik775",
    "nugvsnu",
    "nuhhjnx",
    "nuen3cv",
    "nuaxzqe",
    "nujr797",
    "nuaq36s",
    "nuoq7n1",
    "nuklc60",
    "nuk45mv",
    "nulr8so",
    "nuhg8jk",
    "nuc1t5c",
    "nujwgf5",
    "nufvjuk",
    "nudhqjz",
    "nug2bbr",
    "nudu9va",
    "nuhianf",
    "nujw8tb",
    "nuf0p92",
    "nuc7pt3",
    "nudv9zm",
    "nujdyky",
    "nuksnck",
    "nuodsjg",
    "numqwfv",
    "nuemenl",
    "nui7284",
    "nu4dlg7",
    "nu653yj",
    "nuexdbe",
    "nul7doz",
    "nume4un",
    "nultuoj",
    "nugymd5",
    "nukl8qf",
    "nuis5hr",
    "nuavwzp",
    "nuekjdd",
    "nugmo75",
    "nup95i5",
    "nuk0imo",
    "nuhp7n6",
    "nudkkly",
    "nuc9ojm",
    "nupvyys",
    "nulvz7j",
    "nu57kxb",
    "nugmzvc",
    "nuj8f2v",
    "nupsr7h",
    "nul5ggy",
    "nuos3q0",
    "nujrku4",
    "nu555xa",
    "nuag0qd",
    "nuj6fva",
    "nulz11f",
    "nulqcq2",
    "nu5lja9",
    "nu9g5i5",
    "nugicbp",
    "nueq41z",
    "nud5scy",
    "nuprmdm",
    "nu93a5b",
    "nuhqf55",
    "nuovul8",
    "nufp0j1",
    "nupevrz",
    "nub283a",
    "nultzvr",
    "nuklv1b",
    "nufeij8",
    "nuiu5y3",
    "nue1gps",
    "nulli7f",
    "nufyzap",
    "nuoghbd",
    "nujgv5x",
    "nueyy4z",
    "nub6c7u",
    "nukm6fi",
    "nuhtt6f",
    "nui1vyh",
    "nuh5d1j",
    "nupc9b7",
    "nueruu8",
    "nuoghdk",
    "nuia4gq",
    "nuo1orq",
    "nukt360",
    "nukeyct",
    "nu7toi7",
    "nud1a5d",
    "numv4jw",
    "nupetvs",
    "nupkrem",
    "nu5kq6h",
    "nua7edq",
    "nuf03l0",
    "nugs74v",
    "nuiveug",
    "nu7hklg",
    "nuegkh2",
    "nuokomw",
    "nu4iayr",
    "numr1oz",
    "nuao9we",
    "nuhvgua",
    "nu68xwa",
    "nubcnj0",
    "nuga9kj",
    "nuepzml",
    "numk5ui",
    "nui9nnv",
    "nuhvwpw",
    "nugsn3q",
    "nuku8on",
    "nue3n9i",
    "nuiz1es",
    "nugxup6",
    "numtmxp",
    "nukoc3x",
    "nu5t4ax",
    "num5mbg",
    "nukpn5g",
    "nueckuz",
    "nupfpyf",
    "nunwc6u",
    "nu8i9ag",
    "nugyjd5",
    "nuimc3k",
    "nujjb8e",
    "nul49v2",
    "nukr6rg",
    "nubnvm8",
    "nuonpxo",
    "nuj9epa",
    "nu7odel",
    "nufpq7u",
    "nucbwrw",
    "nukuufe",
    "nulxnxe",
    "nuersxm",
    "nud6kkw",
    "nul7wvl",
    "nuls1r8",
    "nujvw9s",
    "nu5f28o",
    "nuk182u",
    "nun8mg4",
    "nuix7c4",
    "nufe06f",
    "nuku8g4",
    "numxd6e",
    "nul1941",
    "nu4kq7f",
    "nugeq0b",
    "nukxk0o",
    "nuis6b6",
    "nufmk5e",
    "nuj7dro",
    "nu93y8t",
    "nuotgkn",
    "nulpeze",
    "nueiwcu",
    "nul5boa",
    "nub6qnh",
    "nugyxgd",
    "nuf8ln7",
    "nu5wrpx",
    "nuldzuo",
    "nulvczq",
    "nuf41kl",
    "nun5g27",
    "nu645ln",
    "nuhmw3j",
    "num1516",
    "nuo7p8b",
    "nukx1ec",
    "nukzwey",
    "nufefr1",
    "nuizmfz",
    "nufsvfl",
    "nufavuz",
    "nueqci3",
    "nua3j7u",
    "nudc7b9",
    "nuo9td9",
    "nuksfye",
    "nuo55fg",
    "nu6shrt",
    "nuoeif3",
    "nufziaf",
    "nulja67",
    "nuctz71",
    "numswk4",
    "nudz2rt",
    "nugft8o",
    "nug6xpo",
    "nul57kb",
    "nulewyx",
    "nupl691",
    "nuk2lfv",
    "nujktev",
    "numhqfe",
    "nub56el",
    "nulduls",
    "nup45ju",
    "nue5pxp",
    "nuns2bx",
    "nupgogi",
    "nuo34ut",
    "nujt3ne",
    "nuhke5c",
    "nuaaorx",
    "nu7cvw7",
    "nuo0l33",
    "nu51iw4",
    "nukj2x9",
    "nuj8eqk",
    "nuekrls",
    "nui0fra",
    "nuk3l6k",
    "nultj5k",
    "nupdbvb",
    "num6oy5",
    "nuj9p8g",
    "nug3mel",
    "nu6wgll",
    "nul0eo9",
    "nul6uhu",
    "nui30cf",
    "nulnyvl",
    "nul1t4g",
    "nu69adt",
    "nujkp1x",
    "nuhh9pw",
    "nul1zng",
    "nuj2mev",
    "nulo7o2",
    "nukzv9r",
    "nuedsu7",
    "nuezzeq",
    "nu9o702",
    "nuhxvpg",
    "nuht14g",
    "nukixgd",
    "nuqy1gq",
    "nunn3oi",
    "nu4zfcx",
    "nuimtp4",
    "nu4fx8f",
    "nuadtm3",
    "nuiz4x5",
    "nukpabf",
    "nuin1x2",
    "nuhtnko",
    "nuecxb2",
    "nuk49uq",
    "nue0u73",
    "nu6i8ar",
    "nuj9bli",
    "nug1ibl",
    "nukysk2",
    "nuh6gk9",
    "nuewcrn",
    "nufnck9",
    "nu4ujma",
    "nulbe91",
    "nu5i2zu",
    "nulwrmg",
    "nudym28",
    "nuhusqd",
    "nugzyns",
    "nud68yk",
    "nulfq6k",
    "nupj6qs",
    "nuizd7q",
    "nuf6c5w",
    "nuhzr54",
    "nukpveb",
    "nunrow5",
    "nua2t5z",
    "nuk4u3u",
    "nufe6gr",
    "nui6j5k",
    "nulvd5l",
    "nuiw1mu",
    "nuog3tu",
    "nufkf99",
    "nunltdw",
    "nupgdrr",
    "nuqv11q",
    "nummzjr",
    "nuhrzkt",
    "nufl6kv",
    "nucqfj4",
    "nuiox11",
    "nukzowa",
    "nunj211",
    "nui1diu",
    "nulr5os",
    "nue9uym",
    "nupaojt",
    "nue8zfl",
    "nuaemit",
    "nuozkj1",
    "nujl2qo",
    "nu85jqn",
    "nuk5wyh",
    "nugtsrz",
    "nue4ci6",
    "nup4o9e",
    "nuijihq",
    "nucc54z",
    "nuf06cr",
    "nulovcj",
    "nujo9oy",
    "nuln0c1",
    "nuefxsz",
    "nukweks",
    "nujaswj",
    "nuqexs5",
    "num5jlj",
    "nu9xt62",
    "nug70um",
    "nuewutb",
    "nui4lcv",
    "num32yg",
    "nu5cum5",
    "nui68w5",
    "nulqsea",
    "nu4nzo0",
    "numt8ey",
    "nuh6q42",
    "nuksfjx",
    "nulpjma",
    "nu7piwh",
    "nupnrs2",
    "nui9foq",
    "num7y81",
    "nuknq6k",
    "nuizgds",
    "nukxrb4",
    "nuhnnoh",
    "nukux0e",
    "nuc2gsl",
    "nujrex2",
    "numt5bg",
    "nucah08",
    "nu7tvnd",
    "nune7ro",
    "nujftiq",
    "nul9hrt",
    "nu5aijj",
    "nulh6z3",
    "nums76m",
    "nuktav6",
    "nufnq1p",
    "nu59p2f",
    "nueg8ef",
    "nu68rqi",
    "nupetcc",
    "nuihq8h",
    "numziwq",
    "nugwdvd",
    "nud13p5",
    "nu8c6na",
    "nulalea",
    "nuiw8l4",
    "nugb5tf",
    "nug4gtq",
    "nukl5dj",
    "nu5iabi",
    "nulegg0",
    "nuhxjk3",
    "nueuy47",
    "nueciba",
    "nup7rav",
    "nue5zo1",
    "numo4wh",
    "nuhhm35",
    "nuktmlc",
    "numfb2a",
    "nu9mruz",
    "nuihlek",
    "nujuy0s",
    "nui1d8d",
    "nujeby1",
    "nuq06wn",
    "nufzvrs",
    "nu7kszd",
    "nul8rdf",
    "nufblm8",
    "nujmty1",
    "nubdyx1",
    "nuhh8i5",
    "nultztr",
    "nuhnpou",
    "numg9rp",
    "nufbvg2",
    "nukkfls",
    "nupn510",
    "nukxqq2",
    "nujl4mc",
    "nuf3xml",
    "nudokft",
    "nucudqs",
    "nuf9sqn",
    "nui76cu",
    "nudkbkv",
    "nukssni",
    "nufir7j",
    "nuivtok",
    "nugv09g",
    "nueenys",
    "nu6z945",
    "nuehvoo",
    "nud4y0d",
    "nucww76",
    "nuix6du",
    "nulx19n",
    "nulzxh5",
    "nuhp2w7",
    "nugwtq8",
    "nufka9l",
    "nugj92q",
    "nudr5ii",
    "nu80cuw",
    "nuklphp",
    "nui9air",
    "nuhf2l2",
    "nukpoe0",
    "nuimcg6",
    "numnt8w",
    "numsk98",
    "nud1bxe",
    "num9vol",
    "numrczh",
    "nunrqwk",
    "nu6gt7f",
    "nulbbre",
    "nuic6f7",
    "nuph5g3",
    "nuiov8w",
    "nugq4xn",
    "nueupe3",
    "nuisfvx",
    "nuknhi0",
    "nue8fu9",
    "nu62qo2",
    "nu9kxlo",
    "nuevu1c",
    "nuivu6g",
    "nudoaqo",
    "nuocoxy",
    "nuktcwn",
    "nuczmay",
    "nuod592",
    "nuqvma7",
    "nu4i5bx",
    "nuf7gh2",
    "nuhmrnn",
    "nudm8a9",
    "nuf4s58",
    "nun162i",
    "nudispl",
    "nulq003",
    "nulzc7s",
    "nui8rye",
    "nub6flb",
    "nueq08g",
    "nu7i45r",
    "nui0lge",
    "nuilnea",
    "nue7s36",
    "nu5eegl",
    "nu6rqua",
    "nuoijcp",
    "nult1p6",
    "nunigam",
    "nuo3gfi",
    "nuem5oq",
    "nuh4i1k",
    "nuqmqsr",
    "nu61shy",
    "nupf0o9",
    "nuho2ul",
    "nu8vrne",
    "nuhl9o4",
    "nujg3nf",
    "nukrpxq",
    "nujrnkl",
    "num74vg",
    "nukwgmh",
    "nulwot8",
    "nugllmj",
    "nupsy5d",
    "nuik9pd",
    "nuk5o5f",
    "nukk9fq",
    "nuo7qzm",
    "nufidgn",
    "nue53j1",
    "nuo1xqm",
    "nudjois",
    "nul2liq",
    "nuh9u75",
    "nu6nxx0",
    "nucp06y",
    "nun4e4d",
    "nui8vef",
    "nujixw4",
    "nuas681",
    "nuh9kxf",
    "nui4dlb",
    "nu65dau",
    "nu6rz50",
    "nugnmn2",
    "nuaavm6",
    "nulnhtk",
    "nudtx2g",
    "nuiwlgq",
    "nubruy0",
    "nukeppg",
    "nuix2nh",
    "nuefz61",
    "nul388v",
    "nujby3o",
    "nudyxnq",
    "nuh9g3p",
    "nug5uu2",
    "nujzoj4",
    "nuiuaub",
    "nuifc0d",
    "nufl4vz",
    "nul7xsz",
    "nuje51c",
    "nuoojua",
    "nu7yk3l",
    "nuf0aw0",
    "nukfosv",
    "nuen3xh",
    "nue1n9t",
    "numo3f8",
    "nuokvhm",
    "nuitbjw",
    "nujs0g0",
    "nuko09c",
    "nu6lz5p",
    "nucyvc4",
    "nud0nct",
    "nuibs4b",
    "nucj63m",
    "nunqtij",
    "nue35ut",
    "nuqva8c",
    "nupja53",
    "nu8t20p",
    "nu52mx2",
    "nupn6vo",
    "nuf99yy",
    "nue3sfl",
    "nuiioq0",
    "nuiszj2",
    "nummv6a",
    "nue069t",
    "nuit5yn",
    "nu6o8x3",
    "num54dy",
    "nugq2kw",
    "numzbm3",
    "nuf2zvy",
    "nukta1r",
    "nuqs9ep",
    "nuqr8u9",
    "nul6te3",
    "nup4e1h",
    "nud0nlq",
    "nucno09",
    "nu6st0x",
    "nukoosu",
    "nuq6yiw",
    "nuhywf2",
    "nudlzza",
    "nuel0x6",
    "nuje2up",
    "nul6fp5",
    "nujtdk0",
    "nugelgh",
    "nuihhdo",
    "nuetn1l",
    "nu4akcm",
    "nuk8u83",
    "nufxqu6",
    "nul120q",
    "nubvp8d",
    "nuivoii",
    "nunj9xh",
    "nulolt2",
    "nuldqrs",
    "nucv7fp",
    "nug44rx",
    "nubwy8s",
    "nu7dp1q",
    "nul8y81",
    "nuhq24z",
    "nuhkx2a",
    "nulgzs8",
    "nuh95wh",
    "nukukbt",
    "num0lsm",
    "nuf51sj",
    "nugm8sx",
    "nuiz5gf",
    "nui8b6i",
    "nuqsn39",
    "nuepsuy",
    "nubrejk",
    "nu9fwrw",
    "nudfkgt",
    "nue34ip",
    "nuqvdi7",
    "nulxmb3",
    "nukkcbz",
    "nujyusu",
    "nundhqy",
    "nulfwlf",
    "nuj7e52",
    "nuirwks",
    "nu5qbb9",
    "nue2od2",
    "nugxlkk",
    "nukp7hp",
    "nupcmrq",
    "nul147g",
    "nuelyp5",
    "nukunby",
    "numhq83",
    "nu4tgfv",
    "nulmmql",
    "nup24f8",
    "nudjlgv",
    "nufeq99",
    "nufk5tl",
    "nubbwo8",
    "nu9vjk8",
    "nuofyf6",
    "nue2gnt",
    "nuleq4u",
    "nupnclk",
    "nujim6p",
    "nul35mz",
    "nucpbgg",
    "nufvyp6",
    "nuhj0a2",
    "nu6vzct",
    "nul51k5",
    "nuojb4n",
    "nuiuoqf",
    "nulegex",
    "nuhrmud",
    "nugye2o",
    "nufkybi",
    "nuidolg",
    "nueacnv",
    "nudgien",
    "nu5bvfq",
    "nughqm9",
    "nuh27g2",
    "nulettg",
    "nu8a8az",
    "nu4w1bw",
    "nuks2lu",
    "nuq1c97",
    "nuixpzr",
    "nudmp3f",
    "nu6b2nf",
    "nudyipd",
    "nug5vwo",
    "nup3l67",
    "nulffc4",
    "nu53s33",
    "nug9ypt",
    "nuhbnhy",
    "nuozr9r",
    "nuj88h7",
    "nunhphg",
    "nufr9as",
    "nuizxpq",
    "nucy11q",
    "nuj98lg",
    "nulixap",
    "nu5l9oy",
    "nu54u4c",
    "nukwvs5",
    "nunsigu",
    "nu76ifo",
    "nuf6tjp",
    "nufkas1",
    "numbmi9",
    "nuoda0l",
    "nu5h0et",
    "nuk62pe",
    "nud4fah",
    "nulxyno",
    "nulirzp",
    "numilal",
    "numz215",
    "nu9au6s",
    "nuej1p0",
    "nujopus",
    "nuew03v",
    "nuebfz7",
    "nupo9qw",
    "nulagy7",
    "nuhyv0a",
    "nul37hi",
    "nupdvka",
    "nummv1l",
    "nukm8fr",
    "nujncxb",
    "nu5ue0k",
    "nujxma7",
    "nubcm1t",
    "nulex5x",
    "nuhplsk",
    "nuhul3h",
    "nuepemg",
    "nunq15j",
    "nulmrwi",
    "nuejcke",
    "nudxzx4",
    "nufbdkn",
    "nuc63q8",
    "nu98rsf",
    "nunnqzk",
    "nuqxjhf",
    "nul0ikw",
    "nuluqtq",
    "nufezs7",
    "nueefx5",
    "nue74xn",
    "nuls87w",
    "nucltuu",
    "nucgsqm",
    "nul4xr6",
    "nugvg8r",
    "nujbrxu",
    "nueianm",
    "nuf2w5z",
    "nuk7klr",
    "nuja9oa",
    "nufcxa7",
    "numjjk8",
    "nukb1s8",
    "nuj1r6f",
    "nud6g2w",
    "nukibm2"
  ]
}